{"package":[{"package_id":"02ee0daf0d72c0ed","department_names":["Beauty","Beauty","Beauty","Beauty","Electronics"],"products":["Makeup","Cream","Makeup","Cream","Headphones"],"colors":["silver","silver","silver","azure","plum"],"product_price":"1372$","taxes":"933$","shipment_cost":"120$","size":"medium","description":"Boston's most advanced compression wear technology increases muscle oxygenation, stabilizes active muscles","sender_first_name":"Helen","sender_last_name":"Cassin","sender_gender":"Female","sender_email_adress":"helencassin53@spotify.com","sender_country":"Luxembourg","sender_state/region":"n/a","sender_city":"Esch sur Alzette","sender_street_name":"Ena Path","sender_street_num":"9656","sender_zipCode":"53706-7601","sender_phone":"(327) 848-2394","reciver_first_name":"Alexis","reciver_last_name":"Ernser","reciver_gender":"Female","reciver_email_adress":"alexisernser94@yahoo.com","reciver_country":"Israel","reciver_state/region":"Arava","reciver_city":"Eilat","reciver_street_name":"Hardoff","reciver_street_num":"73","reciver_zipCode":"21747-9652","reciver_phone":"053-1145182","arrival_date":"Sun Mar 20 2022 01:24:03 GMT+0200 (Israel Standard Time)","sent_date":"Sat Mar 19 2022 16:57:35 GMT+0300 (Israel Daylight Time)"}]}