{"package":[{"package_id":"07b0e3a61647cbed","department_names":["Beauty","Tools","Tools","Tools"],"products":["Cream","Hammer","Hammer","Hammer"],"colors":["maroon","pink","magenta","purple"],"product_price":"1215$","taxes":"620$","shipment_cost":"147$","size":"medium","description":"The slim & simple Maple Gaming Keyboard from Dev Byte comes with a sleek body and 7- Color RGB LED Back-lighting for smart functionality","sender_first_name":"Kim","sender_last_name":"Hodkiewicz","sender_gender":"Female","sender_email_adress":"kimhodkiewicz15@spotify.com","sender_country":"Irland","sender_state/region":"n/a","sender_city":"Castlebar","sender_street_name":"Franecki Inlet","sender_street_num":"6651","sender_zipCode":"66121","sender_phone":"(456) 500-1215","reciver_first_name":"Betty","reciver_last_name":"Bartoletti","reciver_gender":"Female","reciver_email_adress":"bettybartoletti79@mailout.com","reciver_country":"Israel","reciver_state/region":"Arava","reciver_city":"Eilat","reciver_street_name":"HaShita","reciver_street_num":"53","reciver_zipCode":"43512","reciver_phone":"052-8060158","arrival_date":"Sun Mar 20 2022 11:01:34 GMT+0200 (Israel Standard Time)","sent_date":"Sat Mar 19 2022 17:7:5 GMT+0300 (Israel Daylight Time)"}]}