{"package":[{"package_id":"286d6a316fbaebbc","department_names":["Tools","Tools","Tools","Electronics"],"products":["Electric-screw-driver","Electric-screw-driver","Screw-driver","Cell Phone"],"colors":["plum","plum","purple","violet"],"product_price":"198$","taxes":"0$","shipment_cost":"66$","size":"small","description":"Ergonomic executive chair upholstered in bonded black leather and PVC padded seat and back for all-day comfort and support","sender_first_name":"Betty","sender_last_name":"O'Hara","sender_gender":"Female","sender_email_adress":"bettyo'hara67@outlook.com","sender_country":"Irland","sender_state/region":"n/a","sender_city":"Castlebar","sender_street_name":"Hildegard Ports","sender_street_num":"2231","sender_zipCode":"09436-8090","sender_phone":"(985) 848-7698","reciver_first_name":"Henrietta","reciver_last_name":"Herzog","reciver_gender":"Female","reciver_email_adress":"henriettaherzog3@outlook.com","reciver_country":"Israel","reciver_state/region":"Galil","reciver_city":"Bet-Rimon","reciver_street_name":"Hayarkon","reciver_street_num":"19","reciver_zipCode":"71249-5531","reciver_phone":"054-3910321","arrival_date":"Sun Mar 20 2022 13:15:30 GMT+0200 (Israel Standard Time)","sent_date":"Sat Mar 19 2022 17:19:16 GMT+0300 (Israel Daylight Time)"}]}