{"package":[{"package_id":"550453d93e005416","department_names":["Sports","Clothing"],"products":["Bike","Shoes"],"colors":["magenta","violet"],"product_price":"1109$","taxes":"50$","shipment_cost":"125$","size":"large","description":"Ergonomic executive chair upholstered in bonded black leather and PVC padded seat and back for all-day comfort and support","sender_first_name":"Cecilia","sender_last_name":"Sporer","sender_gender":"Female","sender_email_adress":"ceciliasporer13@msmail.com","sender country":"Austria","sender state/region":"Lower Austria","sender_city":"Zeil","sender street_name":"Jared Knolls","sender_street_num":"1940","sender_zipCode":"66948","sender_phone":"(384) 311-6536","reciver_first_name":"Marcia","reciver_last_name":"Larkin","reciver_gender":"Female","reciver_email_adress":"marcialarkin26@apple.com","reciver_country":"Israel","reciver_state/region":"Arava","reciver_city":"Eilat","reciver_street_name":"Kibuts Galuyot","reciver_street_num":"34","reciver_zipCode":"16057-7372","reciver_phone":"055-6101423","arrival_date":"Sun Mar 20 2022 09:15:18 GMT+0200 (Israel Standard Time)","sent_date":"Sat Mar 19 2022 18:42:53 GMT+0300 (Israel Daylight Time)"}]}