{"package":[{"package_id":"c245c9c124de6195","department_names":["Beauty","Home","Electronics","Clothing","Electronics","Tools"],"products":["Cream","Soap","Gps","Pants","Cell Phone","Drill"],"colors":["magenta","plum","purple","magenta","pink","silver"],"product_price":"780$","taxes":"663$","shipment_cost":"160$","size":"medium","description":"The beautiful range of Apple Naturalé that has an exciting mix of natural ingredients. With the Goodness of 100% Natural Ingredients","sender_first_name":"Madeline","sender_last_name":"Hoeger","sender_gender":"Female","sender_email_adress":"madelinehoeger39@mailout.com","sender_country":"Poland","sender_state/region":"n/a","sender_city":"Olsztyn","sender_street_name":"Kunze Locks","sender_street_num":"4078","sender_zipCode":"79178-1159","sender_phone":"(814) 415-4616","reciver_first_name":"Nora","reciver_last_name":"DuBuque","reciver_gender":"Female","reciver_email_adress":"noradubuque11@zahav.co.il","reciver_country":"Israel","reciver_state/region":"Arava","reciver_city":"Hatzeva","reciver_street_name":"Frishman","reciver_street_num":"86","reciver_zipCode":"94739-3311","reciver_phone":"057-1642472","arrival_date":"Sun Mar 20 2022 06:20:59 GMT+0200 (Israel Standard Time)","sent_date":"Sat Mar 19 2022 19:55:44 GMT+0300 (Israel Daylight Time)"}]}